{
  "id": "732-680-N--2020-05-05--13.25.08--detections",
  "model": "ResNet50_COCO_best_v2.0.1.h5",
  "summary": {
    "total": 12,
    "car": 8,
    "person": 1,
    "bicycle": 2,
    "bus": 1
  },
  "732-680-N--2020-05-05--13.25.08--detections--1--car--25.2--7x8--57.55v64.63": {
    "type": "car",
    "id": "732-680-N--2020-05-05--13.25.08--detections--1--car--25.2--7x8--57.55v64.63",
    "percentage_probability": 25.1527339220047,
    "box_points": [
      57,
      55,
      64,
      63
    ]
  },
  "732-680-N--2020-05-05--13.25.08--detections--2--car--53.1--8x8--53.64v61.72": {
    "type": "car",
    "id": "732-680-N--2020-05-05--13.25.08--detections--2--car--53.1--8x8--53.64v61.72",
    "percentage_probability": 53.05013656616211,
    "box_points": [
      53,
      64,
      61,
      72
    ]
  },
  "732-680-N--2020-05-05--13.25.08--detections--3--car--48.1--10x7--101.66v111.73": {
    "type": "car",
    "id": "732-680-N--2020-05-05--13.25.08--detections--3--car--48.1--10x7--101.66v111.73",
    "percentage_probability": 48.09502959251404,
    "box_points": [
      101,
      66,
      111,
      73
    ]
  },
  "732-680-N--2020-05-05--13.25.08--detections--4--car--35.9--13x18--2.68v15.86": {
    "type": "car",
    "id": "732-680-N--2020-05-05--13.25.08--detections--4--car--35.9--13x18--2.68v15.86",
    "percentage_probability": 35.876819491386414,
    "box_points": [
      2,
      68,
      15,
      86
    ]
  },
  "732-680-N--2020-05-05--13.25.08--detections--5--car--48.6--15x19--2.75v17.94": {
    "type": "car",
    "id": "732-680-N--2020-05-05--13.25.08--detections--5--car--48.6--15x19--2.75v17.94",
    "percentage_probability": 48.56807589530945,
    "box_points": [
      2,
      75,
      17,
      94
    ]
  },
  "732-680-N--2020-05-05--13.25.08--detections--6--car--31.1--13x11--4.84v17.95": {
    "type": "car",
    "id": "732-680-N--2020-05-05--13.25.08--detections--6--car--31.1--13x11--4.84v17.95",
    "percentage_probability": 31.098932027816772,
    "box_points": [
      4,
      84,
      17,
      95
    ]
  },
  "732-680-N--2020-05-05--13.25.08--detections--7--car--37.9--16x13--117.67v133.80": {
    "type": "car",
    "id": "732-680-N--2020-05-05--13.25.08--detections--7--car--37.9--16x13--117.67v133.80",
    "percentage_probability": 37.85756528377533,
    "box_points": [
      117,
      67,
      133,
      80
    ]
  },
  "732-680-N--2020-05-05--13.25.08--detections--8--person--86.4--18x42--5.178v23.220": {
    "type": "person",
    "id": "732-680-N--2020-05-05--13.25.08--detections--8--person--86.4--18x42--5.178v23.220",
    "percentage_probability": 86.43466234207153,
    "box_points": [
      5,
      178,
      23,
      220
    ]
  },
  "732-680-N--2020-05-05--13.25.08--detections--9--bicycle--29.7--16x30--8.190v24.220": {
    "type": "bicycle",
    "id": "732-680-N--2020-05-05--13.25.08--detections--9--bicycle--29.7--16x30--8.190v24.220",
    "percentage_probability": 29.726672172546387,
    "box_points": [
      8,
      190,
      24,
      220
    ]
  },
  "732-680-N--2020-05-05--13.25.08--detections--10--bicycle--42.7--15x15--12.207v27.222": {
    "type": "bicycle",
    "id": "732-680-N--2020-05-05--13.25.08--detections--10--bicycle--42.7--15x15--12.207v27.222",
    "percentage_probability": 42.718854546546936,
    "box_points": [
      12,
      207,
      27,
      222
    ]
  },
  "732-680-N--2020-05-05--13.25.08--detections--11--bus--68.5--51x57--31.137v82.194": {
    "type": "bus",
    "id": "732-680-N--2020-05-05--13.25.08--detections--11--bus--68.5--51x57--31.137v82.194",
    "percentage_probability": 68.531733751297,
    "box_points": [
      31,
      137,
      82,
      194
    ]
  },
  "732-680-N--2020-05-05--13.25.08--detections--12--car--91.4--71x57--201.114v272.171": {
    "type": "car",
    "id": "732-680-N--2020-05-05--13.25.08--detections--12--car--91.4--71x57--201.114v272.171",
    "percentage_probability": 91.37004613876343,
    "box_points": [
      201,
      114,
      272,
      171
    ]
  }
}
