{
  "id": "732-680-N--2020-05-05--13.24.17--detections",
  "model": "ResNet50_COCO_best_v2.0.1.h5",
  "summary": {
    "total": 10,
    "car": 9,
    "bus": 1
  },
  "732-680-N--2020-05-05--13.24.17--detections--1--car--25.3--8x9--71.54v79.63": {
    "type": "car",
    "id": "732-680-N--2020-05-05--13.24.17--detections--1--car--25.3--8x9--71.54v79.63",
    "percentage_probability": 25.319617986679077,
    "box_points": [
      71,
      54,
      79,
      63
    ]
  },
  "732-680-N--2020-05-05--13.24.17--detections--2--car--46.2--8x6--64.63v72.69": {
    "type": "car",
    "id": "732-680-N--2020-05-05--13.24.17--detections--2--car--46.2--8x6--64.63v72.69",
    "percentage_probability": 46.22052609920502,
    "box_points": [
      64,
      63,
      72,
      69
    ]
  },
  "732-680-N--2020-05-05--13.24.17--detections--3--car--63.0--10x6--92.63v102.69": {
    "type": "car",
    "id": "732-680-N--2020-05-05--13.24.17--detections--3--car--63.0--10x6--92.63v102.69",
    "percentage_probability": 62.9585862159729,
    "box_points": [
      92,
      63,
      102,
      69
    ]
  },
  "732-680-N--2020-05-05--13.24.17--detections--4--car--60.7--11x7--56.67v67.74": {
    "type": "car",
    "id": "732-680-N--2020-05-05--13.24.17--detections--4--car--60.7--11x7--56.67v67.74",
    "percentage_probability": 60.72821021080017,
    "box_points": [
      56,
      67,
      67,
      74
    ]
  },
  "732-680-N--2020-05-05--13.24.17--detections--5--car--65.3--14x10--80.71v94.81": {
    "type": "car",
    "id": "732-680-N--2020-05-05--13.24.17--detections--5--car--65.3--14x10--80.71v94.81",
    "percentage_probability": 65.2922511100769,
    "box_points": [
      80,
      71,
      94,
      81
    ]
  },
  "732-680-N--2020-05-05--13.24.17--detections--6--car--46.3--14x17--3.78v17.95": {
    "type": "car",
    "id": "732-680-N--2020-05-05--13.24.17--detections--6--car--46.3--14x17--3.78v17.95",
    "percentage_probability": 46.32995128631592,
    "box_points": [
      3,
      78,
      17,
      95
    ]
  },
  "732-680-N--2020-05-05--13.24.17--detections--7--car--75.1--28x12--183.91v211.103": {
    "type": "car",
    "id": "732-680-N--2020-05-05--13.24.17--detections--7--car--75.1--28x12--183.91v211.103",
    "percentage_probability": 75.06289482116699,
    "box_points": [
      183,
      91,
      211,
      103
    ]
  },
  "732-680-N--2020-05-05--13.24.17--detections--8--car--40.7--16x28--1.66v17.94": {
    "type": "car",
    "id": "732-680-N--2020-05-05--13.24.17--detections--8--car--40.7--16x28--1.66v17.94",
    "percentage_probability": 40.690428018569946,
    "box_points": [
      1,
      66,
      17,
      94
    ]
  },
  "732-680-N--2020-05-05--13.24.17--detections--9--car--87.8--24x19--98.83v122.102": {
    "type": "car",
    "id": "732-680-N--2020-05-05--13.24.17--detections--9--car--87.8--24x19--98.83v122.102",
    "percentage_probability": 87.76182532310486,
    "box_points": [
      98,
      83,
      122,
      102
    ]
  },
  "732-680-N--2020-05-05--13.24.17--detections--10--bus--46.6--49x53--30.137v79.190": {
    "type": "bus",
    "id": "732-680-N--2020-05-05--13.24.17--detections--10--bus--46.6--49x53--30.137v79.190",
    "percentage_probability": 46.57683074474335,
    "box_points": [
      30,
      137,
      79,
      190
    ]
  }
}
