{
  "id": "732-680-N--2020-05-05--13.38.33--detections",
  "model": "ResNet50_COCO_best_v2.0.1.h5",
  "summary": {
    "total": 14,
    "car": 14
  },
  "732-680-N--2020-05-05--13.38.33--detections--1--car--31.8--12x11--49.59v61.70": {
    "type": "car",
    "id": "732-680-N--2020-05-05--13.38.33--detections--1--car--31.8--12x11--49.59v61.70",
    "percentage_probability": 31.778842210769653,
    "box_points": [
      49,
      59,
      61,
      70
    ]
  },
  "732-680-N--2020-05-05--13.38.33--detections--2--car--39.4--9x8--51.62v60.70": {
    "type": "car",
    "id": "732-680-N--2020-05-05--13.38.33--detections--2--car--39.4--9x8--51.62v60.70",
    "percentage_probability": 39.36187028884888,
    "box_points": [
      51,
      62,
      60,
      70
    ]
  },
  "732-680-N--2020-05-05--13.38.33--detections--3--car--49.5--10x8--66.65v76.73": {
    "type": "car",
    "id": "732-680-N--2020-05-05--13.38.33--detections--3--car--49.5--10x8--66.65v76.73",
    "percentage_probability": 49.49328005313873,
    "box_points": [
      66,
      65,
      76,
      73
    ]
  },
  "732-680-N--2020-05-05--13.38.33--detections--4--car--28.2--14x11--2.68v16.79": {
    "type": "car",
    "id": "732-680-N--2020-05-05--13.38.33--detections--4--car--28.2--14x11--2.68v16.79",
    "percentage_probability": 28.215712308883667,
    "box_points": [
      2,
      68,
      16,
      79
    ]
  },
  "732-680-N--2020-05-05--13.38.33--detections--5--car--33.6--10x8--59.69v69.77": {
    "type": "car",
    "id": "732-680-N--2020-05-05--13.38.33--detections--5--car--33.6--10x8--59.69v69.77",
    "percentage_probability": 33.572277426719666,
    "box_points": [
      59,
      69,
      69,
      77
    ]
  },
  "732-680-N--2020-05-05--13.38.33--detections--6--car--29.9--14x15--2.74v16.89": {
    "type": "car",
    "id": "732-680-N--2020-05-05--13.38.33--detections--6--car--29.9--14x15--2.74v16.89",
    "percentage_probability": 29.873329401016235,
    "box_points": [
      2,
      74,
      16,
      89
    ]
  },
  "732-680-N--2020-05-05--13.38.33--detections--7--car--69.8--18x10--123.77v141.87": {
    "type": "car",
    "id": "732-680-N--2020-05-05--13.38.33--detections--7--car--69.8--18x10--123.77v141.87",
    "percentage_probability": 69.81313824653625,
    "box_points": [
      123,
      77,
      141,
      87
    ]
  },
  "732-680-N--2020-05-05--13.38.33--detections--8--car--86.6--15x11--62.75v77.86": {
    "type": "car",
    "id": "732-680-N--2020-05-05--13.38.33--detections--8--car--86.6--15x11--62.75v77.86",
    "percentage_probability": 86.57122850418091,
    "box_points": [
      62,
      75,
      77,
      86
    ]
  },
  "732-680-N--2020-05-05--13.38.33--detections--9--car--74.8--14x17--3.78v17.95": {
    "type": "car",
    "id": "732-680-N--2020-05-05--13.38.33--detections--9--car--74.8--14x17--3.78v17.95",
    "percentage_probability": 74.80456829071045,
    "box_points": [
      3,
      78,
      17,
      95
    ]
  },
  "732-680-N--2020-05-05--13.38.33--detections--10--car--57.8--29x18--143.93v172.111": {
    "type": "car",
    "id": "732-680-N--2020-05-05--13.38.33--detections--10--car--57.8--29x18--143.93v172.111",
    "percentage_probability": 57.784342765808105,
    "box_points": [
      143,
      93,
      172,
      111
    ]
  },
  "732-680-N--2020-05-05--13.38.33--detections--11--car--83.4--47x19--275.112v322.131": {
    "type": "car",
    "id": "732-680-N--2020-05-05--13.38.33--detections--11--car--83.4--47x19--275.112v322.131",
    "percentage_probability": 83.35040807723999,
    "box_points": [
      275,
      112,
      322,
      131
    ]
  },
  "732-680-N--2020-05-05--13.38.33--detections--12--car--93.4--68x38--260.130v328.168": {
    "type": "car",
    "id": "732-680-N--2020-05-05--13.38.33--detections--12--car--93.4--68x38--260.130v328.168",
    "percentage_probability": 93.37607622146606,
    "box_points": [
      260,
      130,
      328,
      168
    ]
  },
  "732-680-N--2020-05-05--13.38.33--detections--13--car--25.8--59x59--47.177v106.236": {
    "type": "car",
    "id": "732-680-N--2020-05-05--13.38.33--detections--13--car--25.8--59x59--47.177v106.236",
    "percentage_probability": 25.790059566497803,
    "box_points": [
      47,
      177,
      106,
      236
    ]
  },
  "732-680-N--2020-05-05--13.38.33--detections--14--car--28.3--64x21--78.216v142.237": {
    "type": "car",
    "id": "732-680-N--2020-05-05--13.38.33--detections--14--car--28.3--64x21--78.216v142.237",
    "percentage_probability": 28.285467624664307,
    "box_points": [
      78,
      216,
      142,
      237
    ]
  }
}
