{
  "id": "732-680-N--2020-05-05--13.38.39--detections",
  "model": "ResNet50_COCO_best_v2.0.1.h5",
  "summary": {
    "total": 18,
    "car": 18
  },
  "732-680-N--2020-05-05--13.38.39--detections--1--car--28.0--8x8--47.58v55.66": {
    "type": "car",
    "id": "732-680-N--2020-05-05--13.38.39--detections--1--car--28.0--8x8--47.58v55.66",
    "percentage_probability": 27.950718998908997,
    "box_points": [
      47,
      58,
      55,
      66
    ]
  },
  "732-680-N--2020-05-05--13.38.39--detections--2--car--35.0--8x6--52.65v60.71": {
    "type": "car",
    "id": "732-680-N--2020-05-05--13.38.39--detections--2--car--35.0--8x6--52.65v60.71",
    "percentage_probability": 34.978294372558594,
    "box_points": [
      52,
      65,
      60,
      71
    ]
  },
  "732-680-N--2020-05-05--13.38.39--detections--3--car--44.0--11x7--89.65v100.72": {
    "type": "car",
    "id": "732-680-N--2020-05-05--13.38.39--detections--3--car--44.0--11x7--89.65v100.72",
    "percentage_probability": 44.03209090232849,
    "box_points": [
      89,
      65,
      100,
      72
    ]
  },
  "732-680-N--2020-05-05--13.38.39--detections--4--car--29.8--14x15--2.67v16.82": {
    "type": "car",
    "id": "732-680-N--2020-05-05--13.38.39--detections--4--car--29.8--14x15--2.67v16.82",
    "percentage_probability": 29.820215702056885,
    "box_points": [
      2,
      67,
      16,
      82
    ]
  },
  "732-680-N--2020-05-05--13.38.39--detections--5--car--55.7--14x9--73.68v87.77": {
    "type": "car",
    "id": "732-680-N--2020-05-05--13.38.39--detections--5--car--55.7--14x9--73.68v87.77",
    "percentage_probability": 55.732083320617676,
    "box_points": [
      73,
      68,
      87,
      77
    ]
  },
  "732-680-N--2020-05-05--13.38.39--detections--6--car--34.2--15x15--2.73v17.88": {
    "type": "car",
    "id": "732-680-N--2020-05-05--13.38.39--detections--6--car--34.2--15x15--2.73v17.88",
    "percentage_probability": 34.152355790138245,
    "box_points": [
      2,
      73,
      17,
      88
    ]
  },
  "732-680-N--2020-05-05--13.38.39--detections--7--car--66.6--18x13--80.77v98.90": {
    "type": "car",
    "id": "732-680-N--2020-05-05--13.38.39--detections--7--car--66.6--18x13--80.77v98.90",
    "percentage_probability": 66.56152606010437,
    "box_points": [
      80,
      77,
      98,
      90
    ]
  },
  "732-680-N--2020-05-05--13.38.39--detections--8--car--69.1--15x17--2.78v17.95": {
    "type": "car",
    "id": "732-680-N--2020-05-05--13.38.39--detections--8--car--69.1--15x17--2.78v17.95",
    "percentage_probability": 69.11507248878479,
    "box_points": [
      2,
      78,
      17,
      95
    ]
  },
  "732-680-N--2020-05-05--13.38.39--detections--9--car--81.1--18x12--60.80v78.92": {
    "type": "car",
    "id": "732-680-N--2020-05-05--13.38.39--detections--9--car--81.1--18x12--60.80v78.92",
    "percentage_probability": 81.12164735794067,
    "box_points": [
      60,
      80,
      78,
      92
    ]
  },
  "732-680-N--2020-05-05--13.38.39--detections--10--car--42.2--12x9--149.92v161.101": {
    "type": "car",
    "id": "732-680-N--2020-05-05--13.38.39--detections--10--car--42.2--12x9--149.92v161.101",
    "percentage_probability": 42.24822223186493,
    "box_points": [
      149,
      92,
      161,
      101
    ]
  },
  "732-680-N--2020-05-05--13.38.39--detections--11--car--67.3--26x17--125.86v151.103": {
    "type": "car",
    "id": "732-680-N--2020-05-05--13.38.39--detections--11--car--67.3--26x17--125.86v151.103",
    "percentage_probability": 67.3009991645813,
    "box_points": [
      125,
      86,
      151,
      103
    ]
  },
  "732-680-N--2020-05-05--13.38.39--detections--12--car--34.6--48x24--256.116v304.140": {
    "type": "car",
    "id": "732-680-N--2020-05-05--13.38.39--detections--12--car--34.6--48x24--256.116v304.140",
    "percentage_probability": 34.56797003746033,
    "box_points": [
      256,
      116,
      304,
      140
    ]
  },
  "732-680-N--2020-05-05--13.38.39--detections--13--car--36.3--20x15--284.119v304.134": {
    "type": "car",
    "id": "732-680-N--2020-05-05--13.38.39--detections--13--car--36.3--20x15--284.119v304.134",
    "percentage_probability": 36.29252314567566,
    "box_points": [
      284,
      119,
      304,
      134
    ]
  },
  "732-680-N--2020-05-05--13.38.39--detections--14--car--85.8--32x21--320.121v352.142": {
    "type": "car",
    "id": "732-680-N--2020-05-05--13.38.39--detections--14--car--85.8--32x21--320.121v352.142",
    "percentage_probability": 85.83157062530518,
    "box_points": [
      320,
      121,
      352,
      142
    ]
  },
  "732-680-N--2020-05-05--13.38.39--detections--15--car--94.0--50x30--153.107v203.137": {
    "type": "car",
    "id": "732-680-N--2020-05-05--13.38.39--detections--15--car--94.0--50x30--153.107v203.137",
    "percentage_probability": 93.95781755447388,
    "box_points": [
      153,
      107,
      203,
      137
    ]
  },
  "732-680-N--2020-05-05--13.38.39--detections--16--car--83.5--60x40--252.118v312.158": {
    "type": "car",
    "id": "732-680-N--2020-05-05--13.38.39--detections--16--car--83.5--60x40--252.118v312.158",
    "percentage_probability": 83.49891304969788,
    "box_points": [
      252,
      118,
      312,
      158
    ]
  },
  "732-680-N--2020-05-05--13.38.39--detections--17--car--40.8--59x58--47.177v106.235": {
    "type": "car",
    "id": "732-680-N--2020-05-05--13.38.39--detections--17--car--40.8--59x58--47.177v106.235",
    "percentage_probability": 40.7951682806015,
    "box_points": [
      47,
      177,
      106,
      235
    ]
  },
  "732-680-N--2020-05-05--13.38.39--detections--18--car--29.5--65x21--78.216v143.237": {
    "type": "car",
    "id": "732-680-N--2020-05-05--13.38.39--detections--18--car--29.5--65x21--78.216v143.237",
    "percentage_probability": 29.481542110443115,
    "box_points": [
      78,
      216,
      143,
      237
    ]
  }
}
