{
  "id": "732-680-N--2020-05-05--13.33.09--detections",
  "model": "ResNet50_COCO_best_v2.0.1.h5",
  "summary": {
    "total": 14,
    "car": 14
  },
  "732-680-N--2020-05-05--13.33.09--detections--1--car--34.9--8x7--83.58v91.65": {
    "type": "car",
    "id": "732-680-N--2020-05-05--13.33.09--detections--1--car--34.9--8x7--83.58v91.65",
    "percentage_probability": 34.9243700504303,
    "box_points": [
      83,
      58,
      91,
      65
    ]
  },
  "732-680-N--2020-05-05--13.33.09--detections--2--car--46.8--8x8--40.63v48.71": {
    "type": "car",
    "id": "732-680-N--2020-05-05--13.33.09--detections--2--car--46.8--8x8--40.63v48.71",
    "percentage_probability": 46.76600396633148,
    "box_points": [
      40,
      63,
      48,
      71
    ]
  },
  "732-680-N--2020-05-05--13.33.09--detections--3--car--50.5--8x8--56.63v64.71": {
    "type": "car",
    "id": "732-680-N--2020-05-05--13.33.09--detections--3--car--50.5--8x8--56.63v64.71",
    "percentage_probability": 50.548821687698364,
    "box_points": [
      56,
      63,
      64,
      71
    ]
  },
  "732-680-N--2020-05-05--13.33.09--detections--4--car--25.6--14x19--2.67v16.86": {
    "type": "car",
    "id": "732-680-N--2020-05-05--13.33.09--detections--4--car--25.6--14x19--2.67v16.86",
    "percentage_probability": 25.635534524917603,
    "box_points": [
      2,
      67,
      16,
      86
    ]
  },
  "732-680-N--2020-05-05--13.33.09--detections--5--car--50.8--11x8--46.70v57.78": {
    "type": "car",
    "id": "732-680-N--2020-05-05--13.33.09--detections--5--car--50.8--11x8--46.70v57.78",
    "percentage_probability": 50.78442096710205,
    "box_points": [
      46,
      70,
      57,
      78
    ]
  },
  "732-680-N--2020-05-05--13.33.09--detections--6--car--67.0--12x10--21.68v33.78": {
    "type": "car",
    "id": "732-680-N--2020-05-05--13.33.09--detections--6--car--67.0--12x10--21.68v33.78",
    "percentage_probability": 67.02967286109924,
    "box_points": [
      21,
      68,
      33,
      78
    ]
  },
  "732-680-N--2020-05-05--13.33.09--detections--7--car--41.6--15x18--2.73v17.91": {
    "type": "car",
    "id": "732-680-N--2020-05-05--13.33.09--detections--7--car--41.6--15x18--2.73v17.91",
    "percentage_probability": 41.63699746131897,
    "box_points": [
      2,
      73,
      17,
      91
    ]
  },
  "732-680-N--2020-05-05--13.33.09--detections--8--car--55.2--14x14--3.81v17.95": {
    "type": "car",
    "id": "732-680-N--2020-05-05--13.33.09--detections--8--car--55.2--14x14--3.81v17.95",
    "percentage_probability": 55.24170994758606,
    "box_points": [
      3,
      81,
      17,
      95
    ]
  },
  "732-680-N--2020-05-05--13.33.09--detections--9--car--69.9--24x11--174.87v198.98": {
    "type": "car",
    "id": "732-680-N--2020-05-05--13.33.09--detections--9--car--69.9--24x11--174.87v198.98",
    "percentage_probability": 69.86808776855469,
    "box_points": [
      174,
      87,
      198,
      98
    ]
  },
  "732-680-N--2020-05-05--13.33.09--detections--10--car--82.5--23x16--101.86v124.102": {
    "type": "car",
    "id": "732-680-N--2020-05-05--13.33.09--detections--10--car--82.5--23x16--101.86v124.102",
    "percentage_probability": 82.46431350708008,
    "box_points": [
      101,
      86,
      124,
      102
    ]
  },
  "732-680-N--2020-05-05--13.33.09--detections--11--car--41.1--48x25--268.102v316.127": {
    "type": "car",
    "id": "732-680-N--2020-05-05--13.33.09--detections--11--car--41.1--48x25--268.102v316.127",
    "percentage_probability": 41.058945655822754,
    "box_points": [
      268,
      102,
      316,
      127
    ]
  },
  "732-680-N--2020-05-05--13.33.09--detections--12--car--85.3--52x36--169.117v221.153": {
    "type": "car",
    "id": "732-680-N--2020-05-05--13.33.09--detections--12--car--85.3--52x36--169.117v221.153",
    "percentage_probability": 85.32377481460571,
    "box_points": [
      169,
      117,
      221,
      153
    ]
  },
  "732-680-N--2020-05-05--13.33.09--detections--13--car--25.3--56x58--49.176v105.234": {
    "type": "car",
    "id": "732-680-N--2020-05-05--13.33.09--detections--13--car--25.3--56x58--49.176v105.234",
    "percentage_probability": 25.34538507461548,
    "box_points": [
      49,
      176,
      105,
      234
    ]
  },
  "732-680-N--2020-05-05--13.33.09--detections--14--car--30.7--64x21--77.216v141.237": {
    "type": "car",
    "id": "732-680-N--2020-05-05--13.33.09--detections--14--car--30.7--64x21--77.216v141.237",
    "percentage_probability": 30.718839168548584,
    "box_points": [
      77,
      216,
      141,
      237
    ]
  }
}
