{
  "id": "732-680-N--2020-05-05--13.49.29--detections",
  "model": "ResNet50_COCO_best_v2.0.1.h5",
  "summary": {
    "total": 7,
    "car": 6,
    "bus": 1
  },
  "732-680-N--2020-05-05--13.49.29--detections--1--car--34.7--7x7--88.58v95.65": {
    "type": "car",
    "id": "732-680-N--2020-05-05--13.49.29--detections--1--car--34.7--7x7--88.58v95.65",
    "percentage_probability": 34.70292687416077,
    "box_points": [
      88,
      58,
      95,
      65
    ]
  },
  "732-680-N--2020-05-05--13.49.29--detections--2--car--32.5--9x10--5.64v14.74": {
    "type": "car",
    "id": "732-680-N--2020-05-05--13.49.29--detections--2--car--32.5--9x10--5.64v14.74",
    "percentage_probability": 32.49857723712921,
    "box_points": [
      5,
      64,
      14,
      74
    ]
  },
  "732-680-N--2020-05-05--13.49.29--detections--3--bus--27.7--17x9--116.74v133.83": {
    "type": "bus",
    "id": "732-680-N--2020-05-05--13.49.29--detections--3--bus--27.7--17x9--116.74v133.83",
    "percentage_probability": 27.667200565338135,
    "box_points": [
      116,
      74,
      133,
      83
    ]
  },
  "732-680-N--2020-05-05--13.49.29--detections--4--car--85.3--14x16--3.79v17.95": {
    "type": "car",
    "id": "732-680-N--2020-05-05--13.49.29--detections--4--car--85.3--14x16--3.79v17.95",
    "percentage_probability": 85.31821370124817,
    "box_points": [
      3,
      79,
      17,
      95
    ]
  },
  "732-680-N--2020-05-05--13.49.29--detections--5--car--69.0--17x10--75.77v92.87": {
    "type": "car",
    "id": "732-680-N--2020-05-05--13.49.29--detections--5--car--69.0--17x10--75.77v92.87",
    "percentage_probability": 68.96538734436035,
    "box_points": [
      75,
      77,
      92,
      87
    ]
  },
  "732-680-N--2020-05-05--13.49.29--detections--6--car--34.0--58x58--48.178v106.236": {
    "type": "car",
    "id": "732-680-N--2020-05-05--13.49.29--detections--6--car--34.0--58x58--48.178v106.236",
    "percentage_probability": 34.03479754924774,
    "box_points": [
      48,
      178,
      106,
      236
    ]
  },
  "732-680-N--2020-05-05--13.49.29--detections--7--car--26.0--63x21--78.216v141.237": {
    "type": "car",
    "id": "732-680-N--2020-05-05--13.49.29--detections--7--car--26.0--63x21--78.216v141.237",
    "percentage_probability": 26.03442072868347,
    "box_points": [
      78,
      216,
      141,
      237
    ]
  }
}
