{
  "id": "732-680-N--2020-05-05--13.54.35--detections",
  "model": "ResNet50_COCO_best_v2.0.1.h5",
  "summary": {
    "total": 14,
    "car": 13,
    "bus": 1
  },
  "732-680-N--2020-05-05--13.54.35--detections--1--car--35.1--10x8--5.64v15.72": {
    "type": "car",
    "id": "732-680-N--2020-05-05--13.54.35--detections--1--car--35.1--10x8--5.64v15.72",
    "percentage_probability": 35.07177531719208,
    "box_points": [
      5,
      64,
      15,
      72
    ]
  },
  "732-680-N--2020-05-05--13.54.35--detections--2--car--26.7--9x8--52.63v61.71": {
    "type": "car",
    "id": "732-680-N--2020-05-05--13.54.35--detections--2--car--26.7--9x8--52.63v61.71",
    "percentage_probability": 26.74964964389801,
    "box_points": [
      52,
      63,
      61,
      71
    ]
  },
  "732-680-N--2020-05-05--13.54.35--detections--3--car--50.6--13x8--118.71v131.79": {
    "type": "car",
    "id": "732-680-N--2020-05-05--13.54.35--detections--3--car--50.6--13x8--118.71v131.79",
    "percentage_probability": 50.57317614555359,
    "box_points": [
      118,
      71,
      131,
      79
    ]
  },
  "732-680-N--2020-05-05--13.54.35--detections--4--car--46.8--14x9--78.70v92.79": {
    "type": "car",
    "id": "732-680-N--2020-05-05--13.54.35--detections--4--car--46.8--14x9--78.70v92.79",
    "percentage_probability": 46.846550703048706,
    "box_points": [
      78,
      70,
      92,
      79
    ]
  },
  "732-680-N--2020-05-05--13.54.35--detections--5--car--31.9--12x8--2.75v14.83": {
    "type": "car",
    "id": "732-680-N--2020-05-05--13.54.35--detections--5--car--31.9--12x8--2.75v14.83",
    "percentage_probability": 31.89820647239685,
    "box_points": [
      2,
      75,
      14,
      83
    ]
  },
  "732-680-N--2020-05-05--13.54.35--detections--6--car--29.5--18x16--77.72v95.88": {
    "type": "car",
    "id": "732-680-N--2020-05-05--13.54.35--detections--6--car--29.5--18x16--77.72v95.88",
    "percentage_probability": 29.54930067062378,
    "box_points": [
      77,
      72,
      95,
      88
    ]
  },
  "732-680-N--2020-05-05--13.54.35--detections--7--car--27.8--14x10--2.78v16.88": {
    "type": "car",
    "id": "732-680-N--2020-05-05--13.54.35--detections--7--car--27.8--14x10--2.78v16.88",
    "percentage_probability": 27.818801999092102,
    "box_points": [
      2,
      78,
      16,
      88
    ]
  },
  "732-680-N--2020-05-05--13.54.35--detections--8--car--66.7--15x16--2.79v17.95": {
    "type": "car",
    "id": "732-680-N--2020-05-05--13.54.35--detections--8--car--66.7--15x16--2.79v17.95",
    "percentage_probability": 66.71878695487976,
    "box_points": [
      2,
      79,
      17,
      95
    ]
  },
  "732-680-N--2020-05-05--13.54.35--detections--9--car--45.0--19x14--79.78v98.92": {
    "type": "car",
    "id": "732-680-N--2020-05-05--13.54.35--detections--9--car--45.0--19x14--79.78v98.92",
    "percentage_probability": 45.02840340137482,
    "box_points": [
      79,
      78,
      98,
      92
    ]
  },
  "732-680-N--2020-05-05--13.54.35--detections--10--car--93.9--29x30--322.149v351.179": {
    "type": "car",
    "id": "732-680-N--2020-05-05--13.54.35--detections--10--car--93.9--29x30--322.149v351.179",
    "percentage_probability": 93.86582374572754,
    "box_points": [
      322,
      149,
      351,
      179
    ]
  },
  "732-680-N--2020-05-05--13.54.35--detections--11--car--45.1--80x51--220.125v300.176": {
    "type": "car",
    "id": "732-680-N--2020-05-05--13.54.35--detections--11--car--45.1--80x51--220.125v300.176",
    "percentage_probability": 45.10419964790344,
    "box_points": [
      220,
      125,
      300,
      176
    ]
  },
  "732-680-N--2020-05-05--13.54.35--detections--12--car--28.6--61x59--46.176v107.235": {
    "type": "car",
    "id": "732-680-N--2020-05-05--13.54.35--detections--12--car--28.6--61x59--46.176v107.235",
    "percentage_probability": 28.594672679901123,
    "box_points": [
      46,
      176,
      107,
      235
    ]
  },
  "732-680-N--2020-05-05--13.54.35--detections--13--car--26.8--63x21--78.217v141.238": {
    "type": "car",
    "id": "732-680-N--2020-05-05--13.54.35--detections--13--car--26.8--63x21--78.217v141.238",
    "percentage_probability": 26.7816960811615,
    "box_points": [
      78,
      217,
      141,
      238
    ]
  },
  "732-680-N--2020-05-05--13.54.35--detections--14--bus--33.1--71x61--37.178v108.239": {
    "type": "bus",
    "id": "732-680-N--2020-05-05--13.54.35--detections--14--bus--33.1--71x61--37.178v108.239",
    "percentage_probability": 33.06816220283508,
    "box_points": [
      37,
      178,
      108,
      239
    ]
  }
}
