{
  "id": "732-680-N--2020-05-05--13.40.03--detections",
  "model": "ResNet50_COCO_best_v2.0.1.h5",
  "summary": {
    "total": 10,
    "car": 8,
    "person": 2
  },
  "732-680-N--2020-05-05--13.40.03--detections--1--car--29.6--8x7--87.61v95.68": {
    "type": "car",
    "id": "732-680-N--2020-05-05--13.40.03--detections--1--car--29.6--8x7--87.61v95.68",
    "percentage_probability": 29.622161388397217,
    "box_points": [
      87,
      61,
      95,
      68
    ]
  },
  "732-680-N--2020-05-05--13.40.03--detections--2--car--36.8--13x10--51.72v64.82": {
    "type": "car",
    "id": "732-680-N--2020-05-05--13.40.03--detections--2--car--36.8--13x10--51.72v64.82",
    "percentage_probability": 36.78241968154907,
    "box_points": [
      51,
      72,
      64,
      82
    ]
  },
  "732-680-N--2020-05-05--13.40.03--detections--3--car--30.6--13x10--3.76v16.86": {
    "type": "car",
    "id": "732-680-N--2020-05-05--13.40.03--detections--3--car--30.6--13x10--3.76v16.86",
    "percentage_probability": 30.620616674423218,
    "box_points": [
      3,
      76,
      16,
      86
    ]
  },
  "732-680-N--2020-05-05--13.40.03--detections--4--car--74.7--14x16--3.79v17.95": {
    "type": "car",
    "id": "732-680-N--2020-05-05--13.40.03--detections--4--car--74.7--14x16--3.79v17.95",
    "percentage_probability": 74.71129298210144,
    "box_points": [
      3,
      79,
      17,
      95
    ]
  },
  "732-680-N--2020-05-05--13.40.03--detections--5--car--90.7--26x16--105.95v131.111": {
    "type": "car",
    "id": "732-680-N--2020-05-05--13.40.03--detections--5--car--90.7--26x16--105.95v131.111",
    "percentage_probability": 90.67807197570801,
    "box_points": [
      105,
      95,
      131,
      111
    ]
  },
  "732-680-N--2020-05-05--13.40.03--detections--6--car--84.6--29x27--322.157v351.184": {
    "type": "car",
    "id": "732-680-N--2020-05-05--13.40.03--detections--6--car--84.6--29x27--322.157v351.184",
    "percentage_probability": 84.60196852684021,
    "box_points": [
      322,
      157,
      351,
      184
    ]
  },
  "732-680-N--2020-05-05--13.40.03--detections--7--person--80.8--16x36--15.174v31.210": {
    "type": "person",
    "id": "732-680-N--2020-05-05--13.40.03--detections--7--person--80.8--16x36--15.174v31.210",
    "percentage_probability": 80.77324628829956,
    "box_points": [
      15,
      174,
      31,
      210
    ]
  },
  "732-680-N--2020-05-05--13.40.03--detections--8--person--26.5--15x35--20.177v35.212": {
    "type": "person",
    "id": "732-680-N--2020-05-05--13.40.03--detections--8--person--26.5--15x35--20.177v35.212",
    "percentage_probability": 26.45866870880127,
    "box_points": [
      20,
      177,
      35,
      212
    ]
  },
  "732-680-N--2020-05-05--13.40.03--detections--9--car--34.3--60x56--47.177v107.233": {
    "type": "car",
    "id": "732-680-N--2020-05-05--13.40.03--detections--9--car--34.3--60x56--47.177v107.233",
    "percentage_probability": 34.26767587661743,
    "box_points": [
      47,
      177,
      107,
      233
    ]
  },
  "732-680-N--2020-05-05--13.40.03--detections--10--car--28.0--63x21--77.216v140.237": {
    "type": "car",
    "id": "732-680-N--2020-05-05--13.40.03--detections--10--car--28.0--63x21--77.216v140.237",
    "percentage_probability": 28.021734952926636,
    "box_points": [
      77,
      216,
      140,
      237
    ]
  }
}
