{
  "id": "732-680-N--2020-05-05--13.58.34--detections",
  "model": "ResNet50_COCO_best_v2.0.1.h5",
  "summary": {
    "total": 9,
    "car": 8,
    "person": 1
  },
  "732-680-N--2020-05-05--13.58.34--detections--1--car--29.6--8x6--49.57v57.63": {
    "type": "car",
    "id": "732-680-N--2020-05-05--13.58.34--detections--1--car--29.6--8x6--49.57v57.63",
    "percentage_probability": 29.55162823200226,
    "box_points": [
      49,
      57,
      57,
      63
    ]
  },
  "732-680-N--2020-05-05--13.58.34--detections--2--car--27.7--8x7--57.57v65.64": {
    "type": "car",
    "id": "732-680-N--2020-05-05--13.58.34--detections--2--car--27.7--8x7--57.57v65.64",
    "percentage_probability": 27.721774578094482,
    "box_points": [
      57,
      57,
      65,
      64
    ]
  },
  "732-680-N--2020-05-05--13.58.34--detections--3--car--33.4--11x5--93.65v104.70": {
    "type": "car",
    "id": "732-680-N--2020-05-05--13.58.34--detections--3--car--33.4--11x5--93.65v104.70",
    "percentage_probability": 33.35425853729248,
    "box_points": [
      93,
      65,
      104,
      70
    ]
  },
  "732-680-N--2020-05-05--13.58.34--detections--4--car--43.2--9x9--5.65v14.74": {
    "type": "car",
    "id": "732-680-N--2020-05-05--13.58.34--detections--4--car--43.2--9x9--5.65v14.74",
    "percentage_probability": 43.18281710147858,
    "box_points": [
      5,
      65,
      14,
      74
    ]
  },
  "732-680-N--2020-05-05--13.58.34--detections--5--car--65.5--16x11--48.72v64.83": {
    "type": "car",
    "id": "732-680-N--2020-05-05--13.58.34--detections--5--car--65.5--16x11--48.72v64.83",
    "percentage_probability": 65.47212600708008,
    "box_points": [
      48,
      72,
      64,
      83
    ]
  },
  "732-680-N--2020-05-05--13.58.34--detections--6--car--75.9--14x17--3.78v17.95": {
    "type": "car",
    "id": "732-680-N--2020-05-05--13.58.34--detections--6--car--75.9--14x17--3.78v17.95",
    "percentage_probability": 75.87206363677979,
    "box_points": [
      3,
      78,
      17,
      95
    ]
  },
  "732-680-N--2020-05-05--13.58.34--detections--7--person--74.1--19x35--4.178v23.213": {
    "type": "person",
    "id": "732-680-N--2020-05-05--13.58.34--detections--7--person--74.1--19x35--4.178v23.213",
    "percentage_probability": 74.05110001564026,
    "box_points": [
      4,
      178,
      23,
      213
    ]
  },
  "732-680-N--2020-05-05--13.58.34--detections--8--car--37.0--59x56--47.178v106.234": {
    "type": "car",
    "id": "732-680-N--2020-05-05--13.58.34--detections--8--car--37.0--59x56--47.178v106.234",
    "percentage_probability": 36.991146206855774,
    "box_points": [
      47,
      178,
      106,
      234
    ]
  },
  "732-680-N--2020-05-05--13.58.34--detections--9--car--25.6--63x22--78.216v141.238": {
    "type": "car",
    "id": "732-680-N--2020-05-05--13.58.34--detections--9--car--25.6--63x22--78.216v141.238",
    "percentage_probability": 25.635942816734314,
    "box_points": [
      78,
      216,
      141,
      238
    ]
  }
}
