{
  "id": "732-680-N--2020-05-05--13.53.15--detections",
  "model": "ResNet50_COCO_best_v2.0.1.h5",
  "summary": {
    "total": 8,
    "car": 8
  },
  "732-680-N--2020-05-05--13.53.15--detections--1--car--37.3--10x10--5.63v15.73": {
    "type": "car",
    "id": "732-680-N--2020-05-05--13.53.15--detections--1--car--37.3--10x10--5.63v15.73",
    "percentage_probability": 37.28187680244446,
    "box_points": [
      5,
      63,
      15,
      73
    ]
  },
  "732-680-N--2020-05-05--13.53.15--detections--2--car--57.9--9x7--52.63v61.70": {
    "type": "car",
    "id": "732-680-N--2020-05-05--13.53.15--detections--2--car--57.9--9x7--52.63v61.70",
    "percentage_probability": 57.883185148239136,
    "box_points": [
      52,
      63,
      61,
      70
    ]
  },
  "732-680-N--2020-05-05--13.53.15--detections--3--car--77.4--15x17--2.78v17.95": {
    "type": "car",
    "id": "732-680-N--2020-05-05--13.53.15--detections--3--car--77.4--15x17--2.78v17.95",
    "percentage_probability": 77.40575075149536,
    "box_points": [
      2,
      78,
      17,
      95
    ]
  },
  "732-680-N--2020-05-05--13.53.15--detections--4--car--45.1--20x11--135.81v155.92": {
    "type": "car",
    "id": "732-680-N--2020-05-05--13.53.15--detections--4--car--45.1--20x11--135.81v155.92",
    "percentage_probability": 45.12677192687988,
    "box_points": [
      135,
      81,
      155,
      92
    ]
  },
  "732-680-N--2020-05-05--13.53.15--detections--5--car--84.3--32x14--204.94v236.108": {
    "type": "car",
    "id": "732-680-N--2020-05-05--13.53.15--detections--5--car--84.3--32x14--204.94v236.108",
    "percentage_probability": 84.34557914733887,
    "box_points": [
      204,
      94,
      236,
      108
    ]
  },
  "732-680-N--2020-05-05--13.53.15--detections--6--car--86.6--47x25--167.115v214.140": {
    "type": "car",
    "id": "732-680-N--2020-05-05--13.53.15--detections--6--car--86.6--47x25--167.115v214.140",
    "percentage_probability": 86.57230138778687,
    "box_points": [
      167,
      115,
      214,
      140
    ]
  },
  "732-680-N--2020-05-05--13.53.15--detections--7--car--35.1--57x56--48.178v105.234": {
    "type": "car",
    "id": "732-680-N--2020-05-05--13.53.15--detections--7--car--35.1--57x56--48.178v105.234",
    "percentage_probability": 35.09087860584259,
    "box_points": [
      48,
      178,
      105,
      234
    ]
  },
  "732-680-N--2020-05-05--13.53.15--detections--8--car--26.8--64x20--78.217v142.237": {
    "type": "car",
    "id": "732-680-N--2020-05-05--13.53.15--detections--8--car--26.8--64x20--78.217v142.237",
    "percentage_probability": 26.777154207229614,
    "box_points": [
      78,
      217,
      142,
      237
    ]
  }
}
