{
  "id": "732-680-N--2020-05-05--13.50.03--detections",
  "model": "ResNet50_COCO_best_v2.0.1.h5",
  "summary": {
    "total": 8,
    "car": 7,
    "person": 1
  },
  "732-680-N--2020-05-05--13.50.03--detections--1--car--44.5--9x10--5.64v14.74": {
    "type": "car",
    "id": "732-680-N--2020-05-05--13.50.03--detections--1--car--44.5--9x10--5.64v14.74",
    "percentage_probability": 44.50420439243317,
    "box_points": [
      5,
      64,
      14,
      74
    ]
  },
  "732-680-N--2020-05-05--13.50.03--detections--2--car--28.1--15x9--110.72v125.81": {
    "type": "car",
    "id": "732-680-N--2020-05-05--13.50.03--detections--2--car--28.1--15x9--110.72v125.81",
    "percentage_probability": 28.05544137954712,
    "box_points": [
      110,
      72,
      125,
      81
    ]
  },
  "732-680-N--2020-05-05--13.50.03--detections--3--car--29.2--13x11--2.77v15.88": {
    "type": "car",
    "id": "732-680-N--2020-05-05--13.50.03--detections--3--car--29.2--13x11--2.77v15.88",
    "percentage_probability": 29.156023263931274,
    "box_points": [
      2,
      77,
      15,
      88
    ]
  },
  "732-680-N--2020-05-05--13.50.03--detections--4--car--82.3--15x16--2.79v17.95": {
    "type": "car",
    "id": "732-680-N--2020-05-05--13.50.03--detections--4--car--82.3--15x16--2.79v17.95",
    "percentage_probability": 82.25046992301941,
    "box_points": [
      2,
      79,
      17,
      95
    ]
  },
  "732-680-N--2020-05-05--13.50.03--detections--5--person--29.6--8x18--330.95v338.113": {
    "type": "person",
    "id": "732-680-N--2020-05-05--13.50.03--detections--5--person--29.6--8x18--330.95v338.113",
    "percentage_probability": 29.550760984420776,
    "box_points": [
      330,
      95,
      338,
      113
    ]
  },
  "732-680-N--2020-05-05--13.50.03--detections--6--car--68.6--44x20--226.95v270.115": {
    "type": "car",
    "id": "732-680-N--2020-05-05--13.50.03--detections--6--car--68.6--44x20--226.95v270.115",
    "percentage_probability": 68.61621737480164,
    "box_points": [
      226,
      95,
      270,
      115
    ]
  },
  "732-680-N--2020-05-05--13.50.03--detections--7--car--94.0--55x33--206.116v261.149": {
    "type": "car",
    "id": "732-680-N--2020-05-05--13.50.03--detections--7--car--94.0--55x33--206.116v261.149",
    "percentage_probability": 93.96771788597107,
    "box_points": [
      206,
      116,
      261,
      149
    ]
  },
  "732-680-N--2020-05-05--13.50.03--detections--8--car--32.6--64x21--78.216v142.237": {
    "type": "car",
    "id": "732-680-N--2020-05-05--13.50.03--detections--8--car--32.6--64x21--78.216v142.237",
    "percentage_probability": 32.64184594154358,
    "box_points": [
      78,
      216,
      142,
      237
    ]
  }
}
