{
  "id": "732-680-N--2020-05-05--13.11.52--detections",
  "model": "ResNet50_COCO_best_v2.0.1.h5",
  "summary": {
    "total": 13,
    "car": 12,
    "bus": 1
  },
  "732-680-N--2020-05-05--13.11.52--detections--1--car--27.1--7x8--73.56v80.64": {
    "type": "car",
    "id": "732-680-N--2020-05-05--13.11.52--detections--1--car--27.1--7x8--73.56v80.64",
    "percentage_probability": 27.13998556137085,
    "box_points": [
      73,
      56,
      80,
      64
    ]
  },
  "732-680-N--2020-05-05--13.11.52--detections--2--car--37.1--7x7--86.59v93.66": {
    "type": "car",
    "id": "732-680-N--2020-05-05--13.11.52--detections--2--car--37.1--7x7--86.59v93.66",
    "percentage_probability": 37.09631562232971,
    "box_points": [
      86,
      59,
      93,
      66
    ]
  },
  "732-680-N--2020-05-05--13.11.52--detections--3--car--28.6--10x9--8.60v18.69": {
    "type": "car",
    "id": "732-680-N--2020-05-05--13.11.52--detections--3--car--28.6--10x9--8.60v18.69",
    "percentage_probability": 28.625118732452393,
    "box_points": [
      8,
      60,
      18,
      69
    ]
  },
  "732-680-N--2020-05-05--13.11.52--detections--4--car--29.9--12x13--3.69v15.82": {
    "type": "car",
    "id": "732-680-N--2020-05-05--13.11.52--detections--4--car--29.9--12x13--3.69v15.82",
    "percentage_probability": 29.88033890724182,
    "box_points": [
      3,
      69,
      15,
      82
    ]
  },
  "732-680-N--2020-05-05--13.11.52--detections--5--car--87.1--14x10--60.70v74.80": {
    "type": "car",
    "id": "732-680-N--2020-05-05--13.11.52--detections--5--car--87.1--14x10--60.70v74.80",
    "percentage_probability": 87.07612156867981,
    "box_points": [
      60,
      70,
      74,
      80
    ]
  },
  "732-680-N--2020-05-05--13.11.52--detections--6--car--26.0--20x11--149.78v169.89": {
    "type": "car",
    "id": "732-680-N--2020-05-05--13.11.52--detections--6--car--26.0--20x11--149.78v169.89",
    "percentage_probability": 26.028957962989807,
    "box_points": [
      149,
      78,
      169,
      89
    ]
  },
  "732-680-N--2020-05-05--13.11.52--detections--7--car--55.5--14x16--3.79v17.95": {
    "type": "car",
    "id": "732-680-N--2020-05-05--13.11.52--detections--7--car--55.5--14x16--3.79v17.95",
    "percentage_probability": 55.45285940170288,
    "box_points": [
      3,
      79,
      17,
      95
    ]
  },
  "732-680-N--2020-05-05--13.11.52--detections--8--car--86.7--41x27--162.108v203.135": {
    "type": "car",
    "id": "732-680-N--2020-05-05--13.11.52--detections--8--car--86.7--41x27--162.108v203.135",
    "percentage_probability": 86.66015863418579,
    "box_points": [
      162,
      108,
      203,
      135
    ]
  },
  "732-680-N--2020-05-05--13.11.52--detections--9--car--98.1--62x34--164.136v226.170": {
    "type": "car",
    "id": "732-680-N--2020-05-05--13.11.52--detections--9--car--98.1--62x34--164.136v226.170",
    "percentage_probability": 98.14044237136841,
    "box_points": [
      164,
      136,
      226,
      170
    ]
  },
  "732-680-N--2020-05-05--13.11.52--detections--10--bus--61.8--49x52--29.137v78.189": {
    "type": "bus",
    "id": "732-680-N--2020-05-05--13.11.52--detections--10--bus--61.8--49x52--29.137v78.189",
    "percentage_probability": 61.81871294975281,
    "box_points": [
      29,
      137,
      78,
      189
    ]
  },
  "732-680-N--2020-05-05--13.11.52--detections--11--car--31.8--59x57--47.178v106.235": {
    "type": "car",
    "id": "732-680-N--2020-05-05--13.11.52--detections--11--car--31.8--59x57--47.178v106.235",
    "percentage_probability": 31.849753856658936,
    "box_points": [
      47,
      178,
      106,
      235
    ]
  },
  "732-680-N--2020-05-05--13.11.52--detections--12--car--25.8--63x20--76.217v139.237": {
    "type": "car",
    "id": "732-680-N--2020-05-05--13.11.52--detections--12--car--25.8--63x20--76.217v139.237",
    "percentage_probability": 25.76594352722168,
    "box_points": [
      76,
      217,
      139,
      237
    ]
  },
  "732-680-N--2020-05-05--13.11.52--detections--13--car--85.9--76x29--168.210v244.239": {
    "type": "car",
    "id": "732-680-N--2020-05-05--13.11.52--detections--13--car--85.9--76x29--168.210v244.239",
    "percentage_probability": 85.87268590927124,
    "box_points": [
      168,
      210,
      244,
      239
    ]
  }
}
