{
  "id": "732-680-N--2020-05-05--13.14.56--detections",
  "model": "ResNet50_COCO_best_v2.0.1.h5",
  "summary": {
    "total": 11,
    "car": 10,
    "bus": 1
  },
  "732-680-N--2020-05-05--13.14.56--detections--1--car--43.9--11x9--83.61v94.70": {
    "type": "car",
    "id": "732-680-N--2020-05-05--13.14.56--detections--1--car--43.9--11x9--83.61v94.70",
    "percentage_probability": 43.87948215007782,
    "box_points": [
      83,
      61,
      94,
      70
    ]
  },
  "732-680-N--2020-05-05--13.14.56--detections--2--car--35.2--9x6--99.62v108.68": {
    "type": "car",
    "id": "732-680-N--2020-05-05--13.14.56--detections--2--car--35.2--9x6--99.62v108.68",
    "percentage_probability": 35.163384675979614,
    "box_points": [
      99,
      62,
      108,
      68
    ]
  },
  "732-680-N--2020-05-05--13.14.56--detections--3--car--27.8--12x13--2.67v14.80": {
    "type": "car",
    "id": "732-680-N--2020-05-05--13.14.56--detections--3--car--27.8--12x13--2.67v14.80",
    "percentage_probability": 27.79867649078369,
    "box_points": [
      2,
      67,
      14,
      80
    ]
  },
  "732-680-N--2020-05-05--13.14.56--detections--4--car--38.8--17x10--122.76v139.86": {
    "type": "car",
    "id": "732-680-N--2020-05-05--13.14.56--detections--4--car--38.8--17x10--122.76v139.86",
    "percentage_probability": 38.841432332992554,
    "box_points": [
      122,
      76,
      139,
      86
    ]
  },
  "732-680-N--2020-05-05--13.14.56--detections--5--car--52.6--14x17--3.78v17.95": {
    "type": "car",
    "id": "732-680-N--2020-05-05--13.14.56--detections--5--car--52.6--14x17--3.78v17.95",
    "percentage_probability": 52.55011320114136,
    "box_points": [
      3,
      78,
      17,
      95
    ]
  },
  "732-680-N--2020-05-05--13.14.56--detections--6--car--62.2--22x11--157.78v179.89": {
    "type": "car",
    "id": "732-680-N--2020-05-05--13.14.56--detections--6--car--62.2--22x11--157.78v179.89",
    "percentage_probability": 62.17446327209473,
    "box_points": [
      157,
      78,
      179,
      89
    ]
  },
  "732-680-N--2020-05-05--13.14.56--detections--7--car--38.3--15x25--1.67v16.92": {
    "type": "car",
    "id": "732-680-N--2020-05-05--13.14.56--detections--7--car--38.3--15x25--1.67v16.92",
    "percentage_probability": 38.33968639373779,
    "box_points": [
      1,
      67,
      16,
      92
    ]
  },
  "732-680-N--2020-05-05--13.14.56--detections--8--car--96.0--31x22--97.96v128.118": {
    "type": "car",
    "id": "732-680-N--2020-05-05--13.14.56--detections--8--car--96.0--31x22--97.96v128.118",
    "percentage_probability": 95.95600366592407,
    "box_points": [
      97,
      96,
      128,
      118
    ]
  },
  "732-680-N--2020-05-05--13.14.56--detections--9--car--66.6--33x17--189.95v222.112": {
    "type": "car",
    "id": "732-680-N--2020-05-05--13.14.56--detections--9--car--66.6--33x17--189.95v222.112",
    "percentage_probability": 66.6247308254242,
    "box_points": [
      189,
      95,
      222,
      112
    ]
  },
  "732-680-N--2020-05-05--13.14.56--detections--10--bus--66.5--49x53--29.137v78.190": {
    "type": "bus",
    "id": "732-680-N--2020-05-05--13.14.56--detections--10--bus--66.5--49x53--29.137v78.190",
    "percentage_probability": 66.52079224586487,
    "box_points": [
      29,
      137,
      78,
      190
    ]
  },
  "732-680-N--2020-05-05--13.14.56--detections--11--car--28.5--58x57--47.178v105.235": {
    "type": "car",
    "id": "732-680-N--2020-05-05--13.14.56--detections--11--car--28.5--58x57--47.178v105.235",
    "percentage_probability": 28.522062301635742,
    "box_points": [
      47,
      178,
      105,
      235
    ]
  }
}
