{
  "id": "732-680-N--2020-05-05--13.44.03--detections",
  "model": "ResNet50_COCO_best_v2.0.1.h5",
  "summary": {
    "total": 18,
    "car": 18
  },
  "732-680-N--2020-05-05--13.44.03--detections--1--car--55.0--9x8--66.65v75.73": {
    "type": "car",
    "id": "732-680-N--2020-05-05--13.44.03--detections--1--car--55.0--9x8--66.65v75.73",
    "percentage_probability": 55.02007603645325,
    "box_points": [
      66,
      65,
      75,
      73
    ]
  },
  "732-680-N--2020-05-05--13.44.03--detections--2--car--53.1--9x6--98.65v107.71": {
    "type": "car",
    "id": "732-680-N--2020-05-05--13.44.03--detections--2--car--53.1--9x6--98.65v107.71",
    "percentage_probability": 53.051865100860596,
    "box_points": [
      98,
      65,
      107,
      71
    ]
  },
  "732-680-N--2020-05-05--13.44.03--detections--3--car--72.3--12x9--77.71v89.80": {
    "type": "car",
    "id": "732-680-N--2020-05-05--13.44.03--detections--3--car--72.3--12x9--77.71v89.80",
    "percentage_probability": 72.26941585540771,
    "box_points": [
      77,
      71,
      89,
      80
    ]
  },
  "732-680-N--2020-05-05--13.44.03--detections--4--car--35.1--14x11--2.76v16.87": {
    "type": "car",
    "id": "732-680-N--2020-05-05--13.44.03--detections--4--car--35.1--14x11--2.76v16.87",
    "percentage_probability": 35.11422574520111,
    "box_points": [
      2,
      76,
      16,
      87
    ]
  },
  "732-680-N--2020-05-05--13.44.03--detections--5--car--34.3--14x9--267.77v281.86": {
    "type": "car",
    "id": "732-680-N--2020-05-05--13.44.03--detections--5--car--34.3--14x9--267.77v281.86",
    "percentage_probability": 34.273600578308105,
    "box_points": [
      267,
      77,
      281,
      86
    ]
  },
  "732-680-N--2020-05-05--13.44.03--detections--6--car--79.9--14x16--3.79v17.95": {
    "type": "car",
    "id": "732-680-N--2020-05-05--13.44.03--detections--6--car--79.9--14x16--3.79v17.95",
    "percentage_probability": 79.92239594459534,
    "box_points": [
      3,
      79,
      17,
      95
    ]
  },
  "732-680-N--2020-05-05--13.44.03--detections--7--car--91.4--16x11--64.83v80.94": {
    "type": "car",
    "id": "732-680-N--2020-05-05--13.44.03--detections--7--car--91.4--16x11--64.83v80.94",
    "percentage_probability": 91.3769006729126,
    "box_points": [
      64,
      83,
      80,
      94
    ]
  },
  "732-680-N--2020-05-05--13.44.03--detections--8--car--35.1--13x17--338.86v351.103": {
    "type": "car",
    "id": "732-680-N--2020-05-05--13.44.03--detections--8--car--35.1--13x17--338.86v351.103",
    "percentage_probability": 35.07495820522308,
    "box_points": [
      338,
      86,
      351,
      103
    ]
  },
  "732-680-N--2020-05-05--13.44.03--detections--9--car--27.7--17x12--71.66v88.78": {
    "type": "car",
    "id": "732-680-N--2020-05-05--13.44.03--detections--9--car--27.7--17x12--71.66v88.78",
    "percentage_probability": 27.699637413024902,
    "box_points": [
      71,
      66,
      88,
      78
    ]
  },
  "732-680-N--2020-05-05--13.44.03--detections--10--car--28.6--37x17--268.76v305.93": {
    "type": "car",
    "id": "732-680-N--2020-05-05--13.44.03--detections--10--car--28.6--37x17--268.76v305.93",
    "percentage_probability": 28.56755554676056,
    "box_points": [
      268,
      76,
      305,
      93
    ]
  },
  "732-680-N--2020-05-05--13.44.03--detections--11--car--82.5--25x18--106.88v131.106": {
    "type": "car",
    "id": "732-680-N--2020-05-05--13.44.03--detections--11--car--82.5--25x18--106.88v131.106",
    "percentage_probability": 82.4664831161499,
    "box_points": [
      106,
      88,
      131,
      106
    ]
  },
  "732-680-N--2020-05-05--13.44.03--detections--12--car--56.7--30x20--144.92v174.112": {
    "type": "car",
    "id": "732-680-N--2020-05-05--13.44.03--detections--12--car--56.7--30x20--144.92v174.112",
    "percentage_probability": 56.65851831436157,
    "box_points": [
      144,
      92,
      174,
      112
    ]
  },
  "732-680-N--2020-05-05--13.44.03--detections--13--car--64.6--40x20--221.102v261.122": {
    "type": "car",
    "id": "732-680-N--2020-05-05--13.44.03--detections--13--car--64.6--40x20--221.102v261.122",
    "percentage_probability": 64.55661654472351,
    "box_points": [
      221,
      102,
      261,
      122
    ]
  },
  "732-680-N--2020-05-05--13.44.03--detections--14--car--93.5--36x29--124.107v160.136": {
    "type": "car",
    "id": "732-680-N--2020-05-05--13.44.03--detections--14--car--93.5--36x29--124.107v160.136",
    "percentage_probability": 93.53358149528503,
    "box_points": [
      124,
      107,
      160,
      136
    ]
  },
  "732-680-N--2020-05-05--13.44.03--detections--15--car--87.7--45x21--283.113v328.134": {
    "type": "car",
    "id": "732-680-N--2020-05-05--13.44.03--detections--15--car--87.7--45x21--283.113v328.134",
    "percentage_probability": 87.73123025894165,
    "box_points": [
      283,
      113,
      328,
      134
    ]
  },
  "732-680-N--2020-05-05--13.44.03--detections--16--car--93.9--67x44--208.124v275.168": {
    "type": "car",
    "id": "732-680-N--2020-05-05--13.44.03--detections--16--car--93.9--67x44--208.124v275.168",
    "percentage_probability": 93.87299418449402,
    "box_points": [
      208,
      124,
      275,
      168
    ]
  },
  "732-680-N--2020-05-05--13.44.03--detections--17--car--29.9--48x53--33.136v81.189": {
    "type": "car",
    "id": "732-680-N--2020-05-05--13.44.03--detections--17--car--29.9--48x53--33.136v81.189",
    "percentage_probability": 29.86750304698944,
    "box_points": [
      33,
      136,
      81,
      189
    ]
  },
  "732-680-N--2020-05-05--13.44.03--detections--18--car--35.4--58x58--48.178v106.236": {
    "type": "car",
    "id": "732-680-N--2020-05-05--13.44.03--detections--18--car--35.4--58x58--48.178v106.236",
    "percentage_probability": 35.38310527801514,
    "box_points": [
      48,
      178,
      106,
      236
    ]
  }
}
